ttcal/__init__.py
ttcal/calfns.py
ttcal/day.py
ttcal/duration.py
ttcal/month.py
ttcal/week.py
ttcal/year.py
ttcal/templatetags/__init__.py
ttcal/templatetags/ttcal_tags.py
ttcal-2.0.5.dist-info/LICENSE
ttcal-2.0.5.dist-info/METADATA
ttcal-2.0.5.dist-info/WHEEL
ttcal-2.0.5.dist-info/top_level.txt
ttcal-2.0.5.dist-info/RECORD
