Metadata-Version: 2.1
Name: ttcal
Version: 2.0.5
Summary: ttcal - calendar operations
Home-page: https://github.com/datakortet/ttcal
Author: Bjorn Pettersen
Author-email: bp@datakortet.no
License: UNKNOWN
Platform: UNKNOWN
Classifier: Development Status :: 5 - Production/Stable
Classifier: Intended Audience :: Developers
Classifier: Programming Language :: Python
Classifier: Programming Language :: Python :: 3
Classifier: Topic :: Software Development :: Libraries
License-File: LICENSE
